auto_LiRPA/__init__.py
auto_LiRPA/backward_bound.py
auto_LiRPA/beta_crown.py
auto_LiRPA/bound_general.py
auto_LiRPA/bound_multi_gpu.py
auto_LiRPA/bound_op_map.py
auto_LiRPA/bound_ops.py
auto_LiRPA/bounded_tensor.py
auto_LiRPA/cuda_utils.py
auto_LiRPA/eps_scheduler.py
auto_LiRPA/forward_bound.py
auto_LiRPA/interval_bound.py
auto_LiRPA/linear_bound.py
auto_LiRPA/optimized_bounds.py
auto_LiRPA/parse_graph.py
auto_LiRPA/patches.py
auto_LiRPA/perturbations.py
auto_LiRPA/solver_module.py
auto_LiRPA/utils.py
auto_LiRPA/wrapper.py
auto_LiRPA/operators/__init__.py
auto_LiRPA/operators/activation.py
auto_LiRPA/operators/base.py
auto_LiRPA/operators/bivariate.py
auto_LiRPA/operators/clampmult.py
auto_LiRPA/operators/constant.py
auto_LiRPA/operators/convolution.py
auto_LiRPA/operators/cut_ops.py
auto_LiRPA/operators/dropout.py
auto_LiRPA/operators/dtype.py
auto_LiRPA/operators/leaf.py
auto_LiRPA/operators/linear.py
auto_LiRPA/operators/logical.py
auto_LiRPA/operators/nonlinear.py
auto_LiRPA/operators/normalization.py
auto_LiRPA/operators/pooling.py
auto_LiRPA/operators/reduce.py
auto_LiRPA/operators/rnn.py
auto_LiRPA/operators/shape.py
auto_LiRPA/operators/softmax.py
auto_LiRPA/operators/solver_utils.py
examples/__init__.py
examples/sequence/__init__.py
examples/sequence/data_utils.py
examples/sequence/lstm.py
examples/sequence/train.py
auto_LiRPA-0.3.dist-info/LICENSE
auto_LiRPA-0.3.dist-info/METADATA
auto_LiRPA-0.3.dist-info/WHEEL
auto_LiRPA-0.3.dist-info/top_level.txt
auto_LiRPA-0.3.dist-info/RECORD
